ezloay/__init__.py
ezloay/andeng.py
ezloay-0.0.1.dist-info/LICENSE
ezloay-0.0.1.dist-info/METADATA
ezloay-0.0.1.dist-info/WHEEL
ezloay-0.0.1.dist-info/top_level.txt
ezloay-0.0.1.dist-info/RECORD
