Metadata-Version: 2.1
Name: ezloay
Version: 0.0.1
Summary: This project provides an easy way to recognize faces usingAI
Home-page: https://github.com/sunjian-github/ezface
Author: DengJianxiang
Author-email: 2262532979@qq.com
License-File: LICENSE
